py_sanic_samples/__init__.py
py_sanic_samples/api/__init__.py
py_sanic_samples/api/content/__init__.py
py_sanic_samples/api/content/authors.py
py_sanic_samples/api/content/static.py
py_sanic_samples/api/info.py
py_sanic_samples/app.py
py_sanic_samples/config/log.py
py_sanic_samples-0.1.0.dist-info/LICENSE
py_sanic_samples-0.1.0.dist-info/WHEEL
py_sanic_samples-0.1.0.dist-info/METADATA
py_sanic_samples-0.1.0.dist-info/RECORD
